tests/types/__init__.py
tests/types/alias/__init__.py
tests/types/alias/test_alias_validation.py
tests/types/any/__init__.py
tests/types/any/test_any_validation.py
tests/types/bool/__init__.py
tests/types/bool/test_bool_validation.py
tests/types/bytes/__init__.py
tests/types/bytes/test_bytes_validation.py
tests/types/const/__init__.py
tests/types/const/test_const_validation.py
tests/types/date_type/__init__.py
tests/types/date_type/test_date_validation.py
tests/types/datetime_type/__init__.py
tests/types/datetime_type/test_datetime_validation.py
tests/types/dict/__init__.py
tests/types/dict/test_dict_optional_validation.py
tests/types/dict/test_dict_validation.py
tests/types/float/__init__.py
tests/types/float/test_float_validation.py
tests/types/int/__init__.py
tests/types/int/test_int_validation.py
tests/types/list/__init__.py
tests/types/list/test_list_contains_validation.py
tests/types/list/test_list_of_validation.py
tests/types/list/test_list_validation.py
tests/types/none/__init__.py
tests/types/none/test_none_validation.py
tests/types/str/__init__.py
tests/types/str/test_str_validation.py
tests/types/uuid4/__init__.py
tests/types/uuid4/test_uuid4_validation.py
valera/__init__.py
valera/_abstract_formatter.py
valera/_formatter.py
valera/_validation_result.py
valera/_validator.py
valera/_version.py
valera/py.typed
valera/errors/__init__.py
valera-1.9.0.dist-info/LICENSE.txt
valera-1.9.0.dist-info/METADATA
valera-1.9.0.dist-info/WHEEL
valera-1.9.0.dist-info/top_level.txt
valera-1.9.0.dist-info/RECORD
