Metadata-Version: 2.1
Name: valera
Version: 1.9.0
Summary: Validator for district42 schema
Home-page: https://github.com/d42-schemas/valera
Author: Nikita Tsvetkov
Author-email: tsv1@fastmail.com
License: Apache-2.0
Project-URL: Docs, https://d42.sh
Project-URL: GitHub, https://github.com/d42-schemas/valera
Classifier: License :: OSI Approved :: Apache Software License
Classifier: Programming Language :: Python :: 3.8
Classifier: Programming Language :: Python :: 3.9
Classifier: Programming Language :: Python :: 3.10
Classifier: Programming Language :: Python :: 3.11
Classifier: Programming Language :: Python :: 3.12
Classifier: Typing :: Typed
Requires-Python: >=3.8
License-File: LICENSE.txt
Requires-Dist: niltype<2.0,>=0.3
Requires-Dist: th<1.0,>=0.3
Requires-Dist: district42<2.0,>=1.8.0
